fastapi_custom_responses/__init__.py
fastapi_custom_responses/errors.py
fastapi_custom_responses/responses.py
fastapi_custom_responses-0.0.15.dist-info/METADATA
fastapi_custom_responses-0.0.15.dist-info/WHEEL
fastapi_custom_responses-0.0.15.dist-info/licenses/LICENSE
fastapi_custom_responses-0.0.15.dist-info/RECORD
