Metadata-Version: 2.4
Name: fastapi-custom-responses
Version: 0.0.15
Summary: FastAPI Custom Responses
License: MIT License
License-File: LICENSE
Author: Julien Kmec
Author-email: me@julien.dev
Requires-Python: >=3.11,<3.15
Classifier: License :: Other/Proprietary License
Classifier: Programming Language :: Python :: 3
Classifier: Programming Language :: Python :: 3.11
Classifier: Programming Language :: Python :: 3.12
Classifier: Programming Language :: Python :: 3.13
Classifier: Programming Language :: Python :: 3.14
Provides-Extra: dev
Requires-Dist: black (>=24.3.0,<25.0.0) ; extra == "dev"
Requires-Dist: fastapi[standard] (>=0.115.14)
Requires-Dist: httpx (>=0.27.0) ; extra == "dev"
Requires-Dist: isort (>=5.12.0,<6.0.0) ; extra == "dev"
Requires-Dist: pydantic (>=2.10.6)
Requires-Dist: pydantic-super-model (>=1.1.2)
Requires-Dist: pylint (>=3.0.1,<4.0.0) ; extra == "dev"
Requires-Dist: pytest (>=8.0.0) ; extra == "dev"
Requires-Dist: pytest-asyncio (>=0.24.0) ; extra == "dev"
